sigili/wiki.py
sigili/article/__init__.py
sigili/article/repository.py
sigili/data/ref.py
sigili-0.0.1.dist-info/METADATA
sigili-0.0.1.dist-info/WHEEL
sigili-0.0.1.dist-info/top_level.txt
sigili-0.0.1.dist-info/RECORD
