Metadata-Version: 2.1
Name: sigili
Version: 0.0.1
Summary: Distributed wiki tools
Author-email: Zone Booth <kinostl@gmail.com>
